data_cleaner_lib/__init__.py
data_cleaner_lib/cleaner.py
data_cleaner_lib/test_data.py
data_cleaner_lib-1.1.dist-info/METADATA
data_cleaner_lib-1.1.dist-info/WHEEL
data_cleaner_lib-1.1.dist-info/licenses/LICENSE.txt
data_cleaner_lib-1.1.dist-info/RECORD
