Metadata-Version: 2.4
Name: data_cleaner_lib
Version: 1.1
Summary: A comprehensive data cleaning library for pandas DataFrames
Author-email: Giri V <srisankargiriv14@gmail.com>
License-Expression: MIT
License-File: LICENSE.txt
Classifier: Operating System :: OS Independent
Classifier: Programming Language :: Python :: 3
Requires-Python: >=3.9
Requires-Dist: numpy>=1.21.0
Requires-Dist: pandas>=1.5.0
Requires-Dist: scipy>=1.7.0
